tuxpy/__init__.py
tuxpy/client.py
tuxpy/collection.py
tuxpy/database.py
tuxpy-1.1.0.dist-info/LICENSE
tuxpy-1.1.0.dist-info/METADATA
tuxpy-1.1.0.dist-info/WHEEL
tuxpy-1.1.0.dist-info/top_level.txt
tuxpy-1.1.0.dist-info/RECORD
