Metadata-Version: 2.1
Name: tuxpy
Version: 1.1.0
Summary: This API was created to operate the TuxDB processes with Python Programming Language.
Home-page: https://github.com/burakpadr/tuxpy
Author: burakpadr
Author-email: b.padir99@gmail.com
License: UNKNOWN
Project-URL: Bug Tracker, https://github.com/burakpadr/tuxpy/issues
Platform: UNKNOWN
Classifier: Programming Language :: Python :: 3
Classifier: License :: OSI Approved :: MIT License
Classifier: Operating System :: OS Independent
License-File: LICENSE
Requires-Dist: requests
